easypass/__init__.py
easypass/easypass.py
easypass-0.1.3.dist-info/LICENSE
easypass-0.1.3.dist-info/METADATA
easypass-0.1.3.dist-info/WHEEL
easypass-0.1.3.dist-info/top_level.txt
easypass-0.1.3.dist-info/RECORD
