Metadata-Version: 2.1
Name: easypass
Version: 0.1.3
Summary: Модуль для простой генерации паролей и почтовых ящиков
Home-page: https://github.com/uprj/easypass.py
Author: Uprj
License: UNKNOWN
Platform: UNKNOWN
Classifier: Programming Language :: Python :: 3.8
Classifier: License :: OSI Approved :: MIT License
Classifier: Operating System :: OS Independent
Requires-Python: >=3.6
